{
  "version": 2,
  "extractor": "papercropper",
  "tables": [
    {
      "url": "assets/tables/arxiv/2607.00927v1/table-001.webp",
      "caption": "",
      "page": 0,
      "index": 1,
      "width": 866,
      "height": 1181,
      "label": "Table"
    },
    {
      "url": "assets/tables/arxiv/2607.00927v1/table-002.webp",
      "caption": "",
      "page": 0,
      "index": 2,
      "width": 863,
      "height": 671,
      "label": "Table"
    },
    {
      "url": "assets/tables/arxiv/2607.00927v1/table-003.webp",
      "caption": "",
      "page": 0,
      "index": 3,
      "width": 873,
      "height": 708,
      "label": "Table"
    },
    {
      "url": "assets/tables/arxiv/2607.00927v1/table-004.webp",
      "caption": "",
      "page": 0,
      "index": 4,
      "width": 875,
      "height": 710,
      "label": "Table"
    },
    {
      "url": "assets/tables/arxiv/2607.00927v1/table-005.webp",
      "caption": "",
      "page": 0,
      "index": 5,
      "width": 859,
      "height": 599,
      "label": "Table"
    },
    {
      "url": "assets/tables/arxiv/2607.00927v1/table-006.webp",
      "caption": "",
      "page": 0,
      "index": 6,
      "width": 871,
      "height": 441,
      "label": "Table"
    },
    {
      "url": "assets/tables/arxiv/2607.00927v1/table-007.webp",
      "caption": "",
      "page": 0,
      "index": 7,
      "width": 873,
      "height": 850,
      "label": "Table"
    },
    {
      "url": "assets/tables/arxiv/2607.00927v1/table-008.webp",
      "caption": "",
      "page": 0,
      "index": 8,
      "width": 875,
      "height": 825,
      "label": "Table"
    },
    {
      "url": "assets/tables/arxiv/2607.00927v1/table-009.webp",
      "caption": "",
      "page": 0,
      "index": 9,
      "width": 874,
      "height": 249,
      "label": "Table"
    },
    {
      "url": "assets/tables/arxiv/2607.00927v1/table-010.webp",
      "caption": "",
      "page": 0,
      "index": 10,
      "width": 866,
      "height": 709,
      "label": "Table"
    },
    {
      "url": "assets/tables/arxiv/2607.00927v1/table-011.webp",
      "caption": "",
      "page": 0,
      "index": 11,
      "width": 866,
      "height": 550,
      "label": "Table"
    },
    {
      "url": "assets/tables/arxiv/2607.00927v1/table-012.webp",
      "caption": "",
      "page": 0,
      "index": 12,
      "width": 872,
      "height": 369,
      "label": "Table"
    },
    {
      "url": "assets/tables/arxiv/2607.00927v1/table-013.webp",
      "caption": "",
      "page": 0,
      "index": 13,
      "width": 863,
      "height": 252,
      "label": "Table"
    }
  ]
}